odoo/addons/ssi_service_quotation_tnc/README.rst
odoo/addons/ssi_service_quotation_tnc/__init__.py
odoo/addons/ssi_service_quotation_tnc/__manifest__.py
odoo/addons/ssi_service_quotation_tnc/models/__init__.py
odoo/addons/ssi_service_quotation_tnc/models/service_quotation.py
odoo/addons/ssi_service_quotation_tnc/static/description/icon.png
odoo14_addon_ssi_service_quotation_tnc-14.0.1.0.0.dist-info/METADATA
odoo14_addon_ssi_service_quotation_tnc-14.0.1.0.0.dist-info/WHEEL
odoo14_addon_ssi_service_quotation_tnc-14.0.1.0.0.dist-info/top_level.txt
odoo14_addon_ssi_service_quotation_tnc-14.0.1.0.0.dist-info/RECORD
